Workbook

Sheet Resumen General
A1: Cuadro de Mando Financiero Personal
A2: Análisis basado en principios de finanzas estructuradas (Regla 50/30/20)
B4: Ingresos Reales | D4: Gastos Totales Reales | F4: Ahorro Total Real | H4: Capacidad de Ahorro
B5: ='Presupuesto Mensual'!D8 | D5: ='Presupuesto Mensual'!D15+'Presupuesto Mensual'!D22 | F5: ='Presupuesto Mensual'!D27 | H5: =(B5-D5)/B5
A9: Evaluación de Salud Financiera (Modelo 50/30/20)
A11: Pilar de Finanzas | B11: Regla Teórica | C11: Tu Presupuesto % | D11: Tu Real % | E11: Estado del Pilar
A12: Gastos Fijos (Necesidades) | B12: 0.5 | C12: ='Presupuesto Mensual'!C15/'Presupuesto Mensual'!C8 | D12: ='Presupuesto Mensual'!D15/'Presupuesto Mensual'!D8 | E12: =IF(D12<=B12,"Saludable","Optimizar Gasto")
A13: Gastos Variables (Deseos) | B13: 0.3 | C13: ='Presupuesto Mensual'!C22/'Presupuesto Mensual'!C8 | D13: ='Presupuesto Mensual'!D22/'Presupuesto Mensual'!D8 | E13: =IF(D13<=B13,"Saludable","Ajustar Caprichos")
A14: Ahorro e Inversión (Futuro) | B14: 0.2 | C14: ='Presupuesto Mensual'!C27/'Presupuesto Mensual'!C8 | D14: ='Presupuesto Mensual'!D27/'Presupuesto Mensual'!D8 | E14: =IF(D14>=B14,"Excelente","Incrementar Ahorro")

Sheet Presupuesto Mensual
A1: Planificador de Presupuesto Mensual Detallado
A3: Categoría | B3: Concepto / Descripción | C3: Presupuestado | D3: Real | E3: Desviación | F3: % Ejecución
A4: INGRESOS
A5: Ingresos Principales | B5: Salario Neto | C5: 3500 | D5: 3500 | E5: =D5-C5 | F5: =D5/C5
A6: Ingresos Secundarios | B6: Freelance / Consultoría | C6: 500 | D6: 500 | E6: =D6-C6 | F6: =D6/C6
A7: Otros Ingresos | B7: Inversiones / Rendimientos | C7: 100 | D7: 100 | E7: =D7-C7 | F7: =D7/C7
A8: Total INGRESOS | C8: =SUM(C5:C7) | D8: =SUM(D5:D7) | E8: =D8-C8 | F8: =D8/C8
A10: GASTOS FIJOS (Necesidades - 50% recomendado)
A11: Vivienda | B11: Alquiler / Hipoteca | C11: 1200 | D11: 1176 | E11: =C11-D11 | F11: =D11/C11
A12: Vivienda | B12: Servicios (Agua, Luz, Gas, Internet) | C12: 180 | D12: 176.4 | E12: =C12-D12 | F12: =D12/C12
A13: Seguros | B13: Seguro Médico / Auto | C13: 150 | D13: 147 | E13: =C13-D13 | F13: =D13/C13
A14: Finanzas | B14: Pago de Deudas / Préstamos | C14: 200 | D14: 196 | E14: =C14-D14 | F14: =D14/C14
A15: Transporte | B15: Combustible / Transporte Público | C15: 120 | D15: 117.6 | E15: =C15-D15 | F15: =D15/C15
A16: Total GASTOS | C16: =SUM(C11:C15) | D16: =SUM(D11:D15) | E16: =C16-D16 | F16: =D16/C16
A18: GASTOS VARIABLES (Deseos - 30% recomendado)
A19: Alimentación | B19: Supermercado | C19: 400 | D19: 392 | E19: =C19-D19 | F19: =D19/C19
A20: Personal | B20: Restaurantes y Ocio | C20: 250 | D20: 245 | E20: =C20-D20 | F20: =D20/C20
A21: Personal | B21: Ropa y Cuidado Personal | C21: 100 | D21: 98 | E21: =C21-D21 | F21: =D21/C21
A22: Educación | B22: Suscripciones y Cursos | C22: 50 | D22: 49 | E22: =C22-D22 | F22: =D22/C22
A23: Otros Gastos | B23: Imprevistos menores | C23: 100 | D23: 98 | E23: =C23-D23 | F23: =D23/C23
A24: Total GASTOS | C24: =SUM(C19:C23) | D24: =SUM(D19:D23) | E24: =C24-D24 | F24: =D24/C24
A26: AHORRO E INVERSIÓN (Futuro - 20% recomendado)
A27: Ahorro | B27: Fondo de Emergencia | C27: 300 | D27: 294 | E27: =C27-D27 | F27: =D27/C27
A28: Inversión | B28: Portafolio de Inversión (Acciones/ETF) | C28: 400 | D28: 392 | E28: =C28-D28 | F28: =D28/C28
A29: Ahorro | B29: Plan de Retiro | C29: 150 | D29: 147 | E29: =C29-D29 | F29: =D29/C29
A30: Total AHORRO | C30: =SUM(C27:C29) | D30: =SUM(D27:D29) | E30: =C30-D30 | F30: =D30/C30
A32: SALDO NETO FINAL (Ingresos - Gastos - Ahorros) | C32: =C8-C15-C22-C27 | D32: =D8-D15-D22-D27
